{
  "channel": "production-direct",
  "product": "gridOS",
  "bundleIdentifier": "com.aaldere1.gridos",
  "version": "1.0.14",
  "build": "22",
  "sourceCommit": "c245751",
  "generatedAt": "2026-06-19T17:53:34Z",
  "artifacts": {
    "dmg": {
      "path": "build/release/production/gridOS-1.0.14-22-c245751.dmg",
      "sha256": "ff78c949c06bfaec170fd56b8d63c66d6a181622fb2c4966d6834ccad4e268f9",
      "sizeBytes": 9023820,
      "codesign": "pass",
      "gatekeeper": "pass",
      "stapler": "pass",
      "appTreeSha256": "2b1ddc05c684ed91c3c7bbb7fe30e0182bab5cae1fe1bd498172741529b882f2"
    },
    "zip": {
      "path": "build/release/production/gridOS-1.0.14-22-c245751.zip",
      "sha256": "46be3c5c3ae9721ba59c195a16d94d8497e1857ec854599e7e7c6328aa8686ba",
      "sizeBytes": 8137914,
      "extractionVerification": "pass",
      "stapler": "pass",
      "appTreeSha256": "be125ab5ea19ade4d87fd601239bde50b4e0d364640e8e729e0f1d47b3793659"
    },
    "appBundle": {
      "notarizedAndStapledForZip": true,
      "codesign": "pass",
      "gatekeeper": "pass",
      "stapler": "pass"
    }
  },
  "notarization": {
    "status": "pass",
    "dmgSubmissionId": "0f629080-a7cd-4d3e-925b-712a21eba262",
    "appTicketSourceSubmissionId": "5a817acf-292f-4581-a30b-1ea093b16a35",
    "zipSubmissionId": "a22c85bc-26ab-4db9-a4fb-a51ec852fc85",
    "evidence": ".planning/phases/12-beta/evidence/beta-notarization-dmg-v1.0.14.md",
    "appEvidence": ".planning/phases/12-beta/evidence/beta-notarization-app-v1.0.14.md",
    "zipEvidence": ".planning/phases/12-beta/evidence/beta-notarization-zip-v1.0.14.md"
  },
  "gatekeeper": {
    "status": "pass",
    "dmgEvidence": ".planning/phases/12-beta/evidence/beta-artifact-verification-dmg-v1.0.14.md",
    "zipEvidence": ".planning/phases/12-beta/evidence/beta-artifact-verification-zip-v1.0.14.md"
  },
  "sparkle": {
    "status": "pass",
    "feedUrl": "https://raw.githubusercontent.com/aaldere1/gridOS/main/appcast.xml",
    "appcast": "appcast.xml",
    "appcastSha256": "4a8a67967c71589028d56e7a25e113085139aa16ebf7bc15a4acab69f9842283",
    "publicEdKey": "nnzeMZKjZFLXB/2A8xiz01Nb+dOrs/5xpO1ig+v6+0A=",
    "feedSignature": "qE/y79PQ/I3mPAVhmOHXa1aTD6oV6dBpgU2DNnMaArL4tp6Kdxceg6W4PTsnJlySfdhlGIlXmyQtLpNlaH4MDQ==",
    "feedSignedLength": 3125,
    "enclosureSignature": "yi6eiKNV7Cj2ZT8hLyfvsD+bLlt/xBsvk/45nG0ObBVGWWgyL00s/qTs83WShMMrVrJVM/bm4NqHYK2ICweaDA==",
    "enclosureLength": 9023820,
    "validation": "xmllint pass; Ed25519 public-key verification passed by scripts/write-sparkle-appcast.sh for feed and DMG enclosure",
    "automaticChecks": true,
    "automaticInstall": true,
    "systemProfiling": false,
    "embeddedHelpersSignedWithSecureTimestamps": true
  },
  "launchSmoke": {
    "status": "artifact-proof-pass",
    "evidence": ".planning/phases/14-production-release/evidence/production-launch-smoke.md",
    "scope": "current-Mac artifact assessment plus committed screenshot inspection; separate clean-Mac proof remains open",
    "version": "1.0.14",
    "build": "22",
    "settingsSoftwareUpdates": "pass",
    "settingsAutomaticChecks": true,
    "settingsAutomaticInstall": true,
    "settingsSystemProfiling": false,
    "newIconIncluded": true,
    "hudSignalScreenshot": "pass",
    "commandHelperScreenshotDropZone": "pass",
    "readmeScreenshotsAvoidTerminalPromptsAndUsernames": true
  },
  "terminalPaneProof": {
    "status": "pass",
    "ciBuildTest": "pass",
    "scope": "Command-T pane creation, Control-Tab/Control-Shift-Tab pane traversal, drag-to-rearrange pane headers, and active-pane behavior covered by unit tests."
  },
  "terminalClipboardProof": {
    "status": "pass",
    "ciBuildTest": "pass",
    "liveAppSmoke": "pass",
    "scope": "Source-pane Select All, source-pane copy, cross-pane copy/paste, selected inactive-pane fallback, active-pane paste routing, blocked-pane isolation, and empty-clipboard fallback behavior covered by tests and live app smoke."
  },
  "terminalStabilityProof": {
    "status": "pass",
    "ciBuildTest": "pass",
    "scope": "Terminal jitter, pasteboard shortcuts, surface update, and top-process baseline retention covered by unit tests."
  },
  "githubRelease": {
    "status": "prepared",
    "url": "https://github.com/aaldere1/gridOS/releases/tag/v1.0.14",
    "publishedAt": null,
    "draft": false,
    "prerelease": false,
    "assets": {
      "dmgDigest": "sha256:ff78c949c06bfaec170fd56b8d63c66d6a181622fb2c4966d6834ccad4e268f9",
      "zipDigest": "sha256:46be3c5c3ae9721ba59c195a16d94d8497e1857ec854599e7e7c6328aa8686ba",
      "appcastDigest": "sha256:4a8a67967c71589028d56e7a25e113085139aa16ebf7bc15a4acab69f9842283"
    },
    "rawMainAppcastDiff": "pending",
    "githubActionsRun": "27840599226",
    "githubActionsConclusion": "success"
  },
  "localUpdateProof": {
    "status": "historical-pass",
    "evidence": ".planning/phases/14-production-release/evidence/local-update-proof.md",
    "scope": "1.0.4 build 12 to 1.0.5 build 13 temporary local install root; not clean-Mac evidence"
  },
  "releaseNotes": "docs/release-notes/v1.0.14.md",
  "remainingValidation": "Run Finder install proof on a separate clean Mac and prove Sparkle update flow from 1.0.13 to 1.0.14."
}
